{
    "name": "Phantom sized",
	"description": "You are flat and a little wider.",
    "type": "origins:multiple",
    "hidden": false,
    "friendermen_join_team": {
        "type": "origins:action_on_callback",
        "execute_chosen_when_orb": true,
        "entity_action_lost": {
            "type": "origins:execute_command",
            "command": "scale reset"
        },
        "entity_action_added": {
            "type": "origins:and",
            "actions": [
                {
                    "type": "origins:execute_command",
                    "command": "scale set pehkui:height .25"
                },
                {
                    "type": "origins:execute_command",
                    "command": "scale set pehkui:width 1.55"
                }
            ]
        }
    }
}
